{
  "meta": {
    "lastRefresh": "2026-06-13 09:10",
    "maxPoints": 729,
    "participants": 30,
    "maxAvailable": 9
  },
  "rows": [
    {
      "rank": 1,
      "player": "Boris",
      "group": 6,
      "ko": 0,
      "bonus": 0,
      "total": 6,
      "prevRank": 1,
      "pointsToday": 0,
      "pctMax": 0.6667
    },
    {
      "rank": 1,
      "player": "Elin",
      "group": 6,
      "ko": 0,
      "bonus": 0,
      "total": 6,
      "prevRank": 1,
      "pointsToday": 0,
      "pctMax": 0.6667
    },
    {
      "rank": 1,
      "player": "Jakob Hägglund",
      "group": 6,
      "ko": 0,
      "bonus": 0,
      "total": 6,
      "prevRank": 1,
      "pointsToday": 0,
      "pctMax": 0.6667
    },
    {
      "rank": 1,
      "player": "Johan Leijonhielm",
      "group": 6,
      "ko": 0,
      "bonus": 0,
      "total": 6,
      "prevRank": 1,
      "pointsToday": 0,
      "pctMax": 0.6667
    },
    {
      "rank": 1,
      "player": "Oscar Hultefors",
      "group": 6,
      "ko": 0,
      "bonus": 0,
      "total": 6,
      "prevRank": 1,
      "pointsToday": 0,
      "pctMax": 0.6667
    },
    {
      "rank": 1,
      "player": "Rickard",
      "group": 6,
      "ko": 0,
      "bonus": 0,
      "total": 6,
      "prevRank": 1,
      "pointsToday": 0,
      "pctMax": 0.6667
    },
    {
      "rank": 1,
      "player": "Solveig",
      "group": 6,
      "ko": 0,
      "bonus": 0,
      "total": 6,
      "prevRank": 1,
      "pointsToday": 0,
      "pctMax": 0.6667
    },
    {
      "rank": 8,
      "player": "Ebba Wikström",
      "group": 4,
      "ko": 0,
      "bonus": 0,
      "total": 4,
      "prevRank": 8,
      "pointsToday": 0,
      "pctMax": 0.4444
    },
    {
      "rank": 8,
      "player": "Ebba Örtenblad",
      "group": 4,
      "ko": 0,
      "bonus": 0,
      "total": 4,
      "prevRank": 8,
      "pointsToday": 0,
      "pctMax": 0.4444
    },
    {
      "rank": 8,
      "player": "Erik Engberg",
      "group": 4,
      "ko": 0,
      "bonus": 0,
      "total": 4,
      "prevRank": 8,
      "pointsToday": 0,
      "pctMax": 0.4444
    },
    {
      "rank": 8,
      "player": "Felice Gelin",
      "group": 4,
      "ko": 0,
      "bonus": 0,
      "total": 4,
      "prevRank": 8,
      "pointsToday": 0,
      "pctMax": 0.4444
    },
    {
      "rank": 8,
      "player": "Lukas Källén",
      "group": 4,
      "ko": 0,
      "bonus": 0,
      "total": 4,
      "prevRank": 8,
      "pointsToday": 0,
      "pctMax": 0.4444
    },
    {
      "rank": 13,
      "player": "Alex J",
      "group": 3,
      "ko": 0,
      "bonus": 0,
      "total": 3,
      "prevRank": 13,
      "pointsToday": 0,
      "pctMax": 0.3333
    },
    {
      "rank": 13,
      "player": "Anna",
      "group": 3,
      "ko": 0,
      "bonus": 0,
      "total": 3,
      "prevRank": 13,
      "pointsToday": 0,
      "pctMax": 0.3333
    },
    {
      "rank": 13,
      "player": "Christoffer",
      "group": 3,
      "ko": 0,
      "bonus": 0,
      "total": 3,
      "prevRank": 13,
      "pointsToday": 0,
      "pctMax": 0.3333
    },
    {
      "rank": 13,
      "player": "Dani",
      "group": 3,
      "ko": 0,
      "bonus": 0,
      "total": 3,
      "prevRank": 13,
      "pointsToday": 0,
      "pctMax": 0.3333
    },
    {
      "rank": 13,
      "player": "Daniel",
      "group": 3,
      "ko": 0,
      "bonus": 0,
      "total": 3,
      "prevRank": 13,
      "pointsToday": 0,
      "pctMax": 0.3333
    },
    {
      "rank": 13,
      "player": "Ebba Lindström",
      "group": 3,
      "ko": 0,
      "bonus": 0,
      "total": 3,
      "prevRank": 13,
      "pointsToday": 0,
      "pctMax": 0.3333
    },
    {
      "rank": 13,
      "player": "Filippa Rosell",
      "group": 3,
      "ko": 0,
      "bonus": 0,
      "total": 3,
      "prevRank": 13,
      "pointsToday": 0,
      "pctMax": 0.3333
    },
    {
      "rank": 13,
      "player": "Gustaf L",
      "group": 3,
      "ko": 0,
      "bonus": 0,
      "total": 3,
      "prevRank": 13,
      "pointsToday": 0,
      "pctMax": 0.3333
    },
    {
      "rank": 13,
      "player": "Jacob Cederberg",
      "group": 3,
      "ko": 0,
      "bonus": 0,
      "total": 3,
      "prevRank": 13,
      "pointsToday": 0,
      "pctMax": 0.3333
    },
    {
      "rank": 22,
      "player": "Andreas Panagos",
      "group": 2,
      "ko": 0,
      "bonus": 0,
      "total": 2,
      "prevRank": 22,
      "pointsToday": 0,
      "pctMax": 0.2222
    },
    {
      "rank": 22,
      "player": "Tim",
      "group": 2,
      "ko": 0,
      "bonus": 0,
      "total": 2,
      "prevRank": 22,
      "pointsToday": 0,
      "pctMax": 0.2222
    },
    {
      "rank": 24,
      "player": "David",
      "group": 1,
      "ko": 0,
      "bonus": 0,
      "total": 1,
      "prevRank": 24,
      "pointsToday": 0,
      "pctMax": 0.1111
    },
    {
      "rank": 24,
      "player": "Frida Björning Lundqvist",
      "group": 1,
      "ko": 0,
      "bonus": 0,
      "total": 1,
      "prevRank": 24,
      "pointsToday": 0,
      "pctMax": 0.1111
    },
    {
      "rank": 24,
      "player": "Klas",
      "group": 1,
      "ko": 0,
      "bonus": 0,
      "total": 1,
      "prevRank": 24,
      "pointsToday": 0,
      "pctMax": 0.1111
    },
    {
      "rank": 24,
      "player": "Ludvig Völcker",
      "group": 1,
      "ko": 0,
      "bonus": 0,
      "total": 1,
      "prevRank": 24,
      "pointsToday": 0,
      "pctMax": 0.1111
    },
    {
      "rank": 24,
      "player": "Matilda",
      "group": 1,
      "ko": 0,
      "bonus": 0,
      "total": 1,
      "prevRank": 24,
      "pointsToday": 0,
      "pctMax": 0.1111
    },
    {
      "rank": 24,
      "player": "Petra",
      "group": 1,
      "ko": 0,
      "bonus": 0,
      "total": 1,
      "prevRank": 24,
      "pointsToday": 0,
      "pctMax": 0.1111
    },
    {
      "rank": 24,
      "player": "Simon",
      "group": 1,
      "ko": 0,
      "bonus": 0,
      "total": 1,
      "prevRank": 24,
      "pointsToday": 0,
      "pctMax": 0.1111
    }
  ]
}